README.rst
setup.py
pyramid_debugtoolbar_mongo/__init__.py
pyramid_debugtoolbar_mongo/operation_tracker.py
pyramid_debugtoolbar_mongo.egg-info/PKG-INFO
pyramid_debugtoolbar_mongo.egg-info/SOURCES.txt
pyramid_debugtoolbar_mongo.egg-info/dependency_links.txt
pyramid_debugtoolbar_mongo.egg-info/not-zip-safe
pyramid_debugtoolbar_mongo.egg-info/top_level.txt
pyramid_debugtoolbar_mongo/panels/__init__.py
pyramid_debugtoolbar_mongo/panels/mongo.py