Metadata-Version: 1.1
Name: pyramid_debugtoolbar_mongo
Version: 0.2.3
Summary: Pyramid debugtoolbar extension for mongo
Home-page: https://github.com/gilles/pyramid_debugtoolbar_mongo
Author: Gilles Devaux
Author-email: gilles.devaux@gmail.com
License: MIT
Platform: UNKNOWN
Classifier: Environment :: Web Environment
Classifier: Framework :: Pyramid
Classifier: Intended Audience :: Developers
Classifier: License :: OSI Approved :: MIT License
Classifier: Operating System :: OS Independent
Classifier: Programming Language :: Python
Classifier: Topic :: Database
Classifier: Topic :: Software Development :: Libraries :: Python Modules
Requires: pyramid_debugtoolbar (>=2.0)
